Metadata-Version: 1.2
Name: Ginzicut
Version: 1.4
Summary: nntp test server for ginzicut
Home-page: https://github.com/dermatty/GINZICUT
Author: dermatty
Author-email: stephan@untergrabner.at
License: UNKNOWN
Keywords: usenet,nntp
Platform: posix
Classifier: Development Status :: 4 - Beta
Classifier: Environment :: Console
Classifier: Programming Language :: Python :: 3.7
Classifier: Programming Language :: Python :: 3.6
Requires-Python: >=3.6.1
